qtgallery/__init__.py
qtgallery/_version.py
qtgallery/qtgallery.py
qtgallery/qtscraper.py
qtgallery-0.0.2.dist-info/LICENSE
qtgallery-0.0.2.dist-info/METADATA
qtgallery-0.0.2.dist-info/WHEEL
qtgallery-0.0.2.dist-info/top_level.txt
qtgallery-0.0.2.dist-info/RECORD
