Metadata-Version: 2.1
Name: qtgallery
Version: 0.0.2
Summary: sphinx-gallery scraper for Qt examples and tutorials
Home-page: UNKNOWN
Author: Kenneth Lyons
Author-email: ixjlyons@gmail.com
License: MIT
Platform: UNKNOWN
Requires-Dist: qtpy
Requires-Dist: pyvirtualdisplay
Requires-Dist: sphinx-gallery
Requires-Dist: pillow
Requires-Dist: sphinx-rtd-theme
